{
	"$schema": "https://raw.githubusercontent.com/felippe-alves/scidekick/main/packages/coding-agent/theme-schema.json",
	"name": "dark",
	"vars": {
		"violet": "#7C5CFC",
		"violetGlow": "#A78BFA",
		"teal": "#00C9DB",
		"tealDeep": "#0098A8",
		"amber": "#F5A623",
		"amberGlow": "#FCC869",
		"green": "#30D158",
		"red": "#FF453A",
		"yellow": "#FFD60A",
		"info": "#64D2FF",
		"gray": "#64748B",
		"dimGray": "#475569",
		"darkGray": "#1E293B",
		"accent": "#F5A623",
		"selectedBg": "#2D1F5E",
		"userMsgBg": "#1A1525",
		"toolPendingBg": "#151221",
		"toolSuccessBg": "#11121A",
		"toolErrorBg": "#201515",
		"customMsgBg": "#1F1A2E"
	},
	"colors": {
		"accent": "amber",
		"border": "violetGlow",
		"borderAccent": "teal",
		"borderMuted": "darkGray",
		"success": "green",
		"error": "red",
		"warning": "yellow",
		"muted": "gray",
		"dim": "dimGray",
		"text": "",
		"thinkingText": "dimGray",
		"selectedBg": "selectedBg",
		"userMessageBg": "userMsgBg",
		"userMessageText": "",
		"customMessageBg": "customMsgBg",
		"customMessageText": "",
		"customMessageLabel": "#A78BFA",
		"toolPendingBg": "toolPendingBg",
		"toolSuccessBg": "toolSuccessBg",
		"toolErrorBg": "toolErrorBg",
		"toolTitle": "",
		"toolOutput": "gray",
		"mdHeading": "#7C5CFC",
		"mdLink": "#00C9DB",
		"mdLinkUrl": "dimGray",
		"mdCode": "#A78BFA",
		"mdCodeBlock": "#00C9DB",
		"mdCodeBlockBorder": "darkGray",
		"mdQuote": "gray",
		"mdQuoteBorder": "darkGray",
		"mdHr": "darkGray",
		"mdListBullet": "#7C5CFC",
		"toolDiffAdded": "green",
		"toolDiffRemoved": "red",
		"toolDiffContext": "gray",
		"link": "#00C9DB",
		"syntaxComment": "#6A9955",
		"syntaxKeyword": "#C586C0",
		"syntaxFunction": "#DCDCAA",
		"syntaxVariable": "#9CDCFE",
		"syntaxString": "#CE9178",
		"syntaxNumber": "#B5CEA8",
		"syntaxType": "#4EC9B0",
		"syntaxOperator": "#D4D4D4",
		"syntaxPunctuation": "#D4D4D4",
		"thinkingOff": "darkGray",
		"thinkingMinimal": "dimGray",
		"thinkingLow": "#5B3FDB",
		"thinkingMedium": "#7C5CFC",
		"thinkingHigh": "#A78BFA",
		"thinkingXhigh": "#FCC869",
		"bashMode": "teal",
		"statusLineBg": "#0B0A14",
		"statusLineSep": 104,
		"statusLineModel": "#A78BFA",
		"statusLinePath": "#00C9DB",
		"statusLineGitClean": "#30D158",
		"statusLineGitDirty": "#F5A623",
		"statusLineContext": "#7C5CFC",
		"statusLineSpend": "#00C9DB",
		"statusLineStaged": 141,
		"statusLineDirty": 214,
		"statusLineUntracked": 141,
		"statusLineOutput": 43,
		"statusLineCost": 43,
		"statusLineSubagents": "amber",
		"pythonMode": "amber"
	},
	"export": {
		"pageBg": "#0B0A14",
		"cardBg": "#131124",
		"infoBg": "#1F1A2E"
	}
}
